selenium_helper/__init__.py
selenium_helper/exceptions.py
selenium_helper/helper.py
selenium_helper-0.1.2.2.dist-info/DESCRIPTION.rst
selenium_helper-0.1.2.2.dist-info/METADATA
selenium_helper-0.1.2.2.dist-info/RECORD
selenium_helper-0.1.2.2.dist-info/WHEEL
selenium_helper-0.1.2.2.dist-info/metadata.json
selenium_helper-0.1.2.2.dist-info/top_level.txt
