Metadata-Version: 2.0
Name: selenium-helper
Version: 0.1.2.2
Summary: UNKNOWN
Home-page: https://github.com/Ammadkhalid/
Author: Ammad Khalid
Author-email: ammadkhalid12@gmail.com
License: UNKNOWN
Platform: UNKNOWN
Requires-Python: >= 3
Requires-Dist: selenium
Requires-Dist: pandas
Requires-Dist: openpyxl
